arda/__init__.py
arda/dates.py
arda/pron.py
arda-0.3.0.dist-info/LICENSE
arda-0.3.0.dist-info/METADATA
arda-0.3.0.dist-info/WHEEL
arda-0.3.0.dist-info/top_level.txt
arda-0.3.0.dist-info/RECORD
