Metadata-Version: 2.1
Name: arda
Version: 0.3.0
Summary: Python library for Tolkien-related data processing
Home-page: http://github.com/digitaltolkien/arda
Author: James Tauber
Author-email: jtauber@jtauber.com
License: MIT
License-File: LICENSE
